google/cloud/logging/__init__.py
google/cloud/logging/gapic_version.py
google/cloud/logging/py.typed
google/cloud/logging/handlers/__init__.py
google/cloud/logging/handlers/middleware/__init__.py
google/cloud/logging/handlers/transports/__init__.py
google/cloud/logging_v2/__init__.py
google/cloud/logging_v2/_gapic.py
google/cloud/logging_v2/_helpers.py
google/cloud/logging_v2/_http.py
google/cloud/logging_v2/_instrumentation.py
google/cloud/logging_v2/client.py
google/cloud/logging_v2/entries.py
google/cloud/logging_v2/gapic_metadata.json
google/cloud/logging_v2/gapic_version.py
google/cloud/logging_v2/logger.py
google/cloud/logging_v2/metric.py
google/cloud/logging_v2/py.typed
google/cloud/logging_v2/resource.py
google/cloud/logging_v2/sink.py
google/cloud/logging_v2/handlers/__init__.py
google/cloud/logging_v2/handlers/_helpers.py
google/cloud/logging_v2/handlers/_monitored_resources.py
google/cloud/logging_v2/handlers/app_engine.py
google/cloud/logging_v2/handlers/container_engine.py
google/cloud/logging_v2/handlers/handlers.py
google/cloud/logging_v2/handlers/structured_log.py
google/cloud/logging_v2/handlers/middleware/__init__.py
google/cloud/logging_v2/handlers/middleware/request.py
google/cloud/logging_v2/handlers/transports/__init__.py
google/cloud/logging_v2/handlers/transports/background_thread.py
google/cloud/logging_v2/handlers/transports/base.py
google/cloud/logging_v2/handlers/transports/sync.py
google/cloud/logging_v2/services/__init__.py
google/cloud/logging_v2/services/config_service_v2/__init__.py
google/cloud/logging_v2/services/config_service_v2/async_client.py
google/cloud/logging_v2/services/config_service_v2/client.py
google/cloud/logging_v2/services/config_service_v2/pagers.py
google/cloud/logging_v2/services/config_service_v2/transports/__init__.py
google/cloud/logging_v2/services/config_service_v2/transports/base.py
google/cloud/logging_v2/services/config_service_v2/transports/grpc.py
google_cloud_logging-3.12.1.dist-info/LICENSE
google_cloud_logging-3.12.1.dist-info/METADATA
google_cloud_logging-3.12.1.dist-info/WHEEL
google_cloud_logging-3.12.1.dist-info/top_level.txt
google_cloud_logging-3.12.1.dist-info/RECORD
